linkedPack/__init__.py
linkedPack/linked.py
linkedpack-0.1.2.dist-info/licenses/LICENSE
linkedpack-0.1.2.dist-info/METADATA
linkedpack-0.1.2.dist-info/WHEEL
linkedpack-0.1.2.dist-info/top_level.txt
linkedpack-0.1.2.dist-info/RECORD
