Metadata-Version: 2.4
Name: linkedPack
Version: 0.1.2
Summary: A simple custom linked list implementation.
Author-email: William Vasquez <will.vasq77@gmail.com>
License: MIT License
Requires-Python: >=3.6
License-File: LICENSE
Dynamic: license-file
